monzo_api_stub-0.1.3.dist-info/DESCRIPTION.rst
monzo_api_stub-0.1.3.dist-info/METADATA
monzo_api_stub-0.1.3.dist-info/RECORD
monzo_api_stub-0.1.3.dist-info/WHEEL
monzo_api_stub-0.1.3.dist-info/entry_points.txt
monzo_api_stub-0.1.3.dist-info/metadata.json
monzo_api_stub-0.1.3.dist-info/top_level.txt
monzoapistub/__init__.py
monzoapistub/cli.py
monzoapistub/database.py
monzoapistub/datatypes.py
monzoapistub/server.py
