Metadata-Version: 2.0
Name: monzo-api-stub
Version: 0.1.3
Summary: Stub API for Monzo
Home-page: https://github.com/danpalmer/monzo-api-stub
Author: Dan Palmer
Author-email: dan@danpalmer.me
License: MIT
Platform: UNKNOWN
Classifier: Development Status :: 4 - Beta
Classifier: Environment :: Console
Classifier: Intended Audience :: Developers
Classifier: License :: OSI Approved :: MIT License
Classifier: Operating System :: OS Independent
Classifier: Programming Language :: Python
Classifier: Programming Language :: Python :: 3
Classifier: Programming Language :: Python :: 3.5
Requires-Dist: click (>=6.6)
Requires-Dist: emoji (>=0.3.9)
Requires-Dist: faker (>=0.8.6)
Requires-Dist: flask (>=0.11)
